dynamodb_cache/__init__.py
dynamodb_cache/_version.py
dynamodb_cache/abstract.py
dynamodb_cache/multi_layer.py
dynamodb_cache/utils.py
dynamodb_cache/backend/__init__.py
dynamodb_cache/backend/dynamodb.py
dynamodb_cache/backend/in_memory.py
dynamodb_cache/docs/__init__.py
dynamodb_cache-0.1.1.dist-info/AUTHORS.rst
dynamodb_cache-0.1.1.dist-info/LICENSE.txt
dynamodb_cache-0.1.1.dist-info/METADATA
dynamodb_cache-0.1.1.dist-info/WHEEL
dynamodb_cache-0.1.1.dist-info/top_level.txt
dynamodb_cache-0.1.1.dist-info/RECORD
